psr/cloud/__init__.py
psr/cloud/aws.py
psr/cloud/cloud.py
psr/cloud/data.py
psr/cloud/desktop.py
psr/cloud/log.py
psr/cloud/status.py
psr/cloud/tempfile.py
psr/cloud/version.py
psr/cloud/xml.py
psr_cloud-0.3.13.dist-info/METADATA
psr_cloud-0.3.13.dist-info/WHEEL
psr_cloud-0.3.13.dist-info/top_level.txt
psr_cloud-0.3.13.dist-info/RECORD
