Metadata-Version: 2.4
Name: psr-cloud
Version: 0.3.13
Summary: PSR Cloud Python Module
Author-email: Lucas Storino <lstorino@psr-inc.com>, Pedro Henrique <pedrohenrique@psr-inc.com>
Requires-Dist: zeep
Requires-Dist: filelock
Requires-Dist: pefile
Requires-Dist: boto3
Requires-Dist: tqdm
